ddpro/__init__.py
ddpro/_readconfig.py
ddpro/basetypes.py
ddpro/main.py
ddpro/plot.py
ddpro/preprocess.py
ddpro/config/config.ini
ddpro-0.0.2.dist-info/LICENSE
ddpro-0.0.2.dist-info/METADATA
ddpro-0.0.2.dist-info/WHEEL
ddpro-0.0.2.dist-info/top_level.txt
ddpro-0.0.2.dist-info/RECORD
